spalipy/__init__.py
spalipy/spalipy.py
spalipy/utils.py
test/__init__.py
test/test_spalipy.py
spalipy-3.5.3.dist-info/LICENSE.txt
spalipy-3.5.3.dist-info/METADATA
spalipy-3.5.3.dist-info/WHEEL
spalipy-3.5.3.dist-info/entry_points.txt
spalipy-3.5.3.dist-info/top_level.txt
spalipy-3.5.3.dist-info/RECORD
