Metadata-Version: 2.1
Name: spalipy
Version: 3.5.3
Summary: Detection-based astrononmical image registration
Home-page: https://github.com/Lyalpha/spalipy
Author: Joe Lyman
Author-email: joedlyman@gmail.com
Classifier: Programming Language :: Python :: 3.8
Classifier: Programming Language :: Python :: 3.9
Classifier: Programming Language :: Python :: 3.10
Classifier: Programming Language :: Python :: 3.11
Classifier: License :: OSI Approved :: GNU General Public License v3 (GPLv3)
Classifier: Operating System :: OS Independent
Classifier: Topic :: Scientific/Engineering :: Astronomy
License-File: LICENSE.txt
Requires-Dist: sep >=1.1.1
Requires-Dist: scipy >=1.1.0
Requires-Dist: numpy >=1.10
Requires-Dist: astropy >=3.2.2
